zope/keyreference/__init__.py
zope/keyreference/configure.zcml
zope/keyreference/interfaces.py
zope/keyreference/persistent.py
zope/keyreference/persistent.txt
zope/keyreference/testing.py
zope/keyreference/tests.py
zope_keyreference-7.0.dist-info/licenses/LICENSE.txt
zope_keyreference-7.0.dist-info/METADATA
zope_keyreference-7.0.dist-info/WHEEL
zope_keyreference-7.0.dist-info/top_level.txt
zope_keyreference-7.0.dist-info/RECORD
